{
    "GRADES":[
        [
            {
                "EXAM_PAPER_PDF_TITLE":"SITTUKKAL First Term 2020",
                "LINK":"https://drive.google.com/file/d/1nhe7TToJqt1UWcFQ427-1JLepS11pnDH/view?usp=sharing"
            },
            {
                "EXAM_PAPER_PDF_TITLE":"Activity 02",
                "LINK":"https://drive.google.com/file/d/1QajbGX_ecRQ6XdZVDLpG224mdumOGDxp/view?usp=sharing"
            },
            {
                "EXAM_PAPER_PDF_TITLE":"Activity 03",
                "LINK":"https://drive.google.com/file/d/1OcCEr3lpvnWbMJwV8Vn50WsRMK1gH3DO/view?usp=sharing"
            },
            {
                "EXAM_PAPER_PDF_TITLE":"Activity 01",
                "LINK":"https://drive.google.com/file/d/1PwbR8ehNKO1O27K9QxHDaE4e8mN2MBLE/view?usp=sharing"
            },
            {
                "EXAM_PAPER_PDF_TITLE":"Activity 05",
                "LINK":"https://drive.google.com/file/d/1Jui7bKGzp5B3BSa56BNoSDySZBfpAdvc/view?usp=sharing"
            }
        ],
        [
            {
                "EXAM_PAPER_PDF_TITLE":"TIMES from e-thaksalawa",
                "LINK":"https://www.e-thaksalawa.moe.gov.lk/moodle/mod/hvp/view.php?id=47138"
            },
            {
                "EXAM_PAPER_PDF_TITLE":"CAPACITY from e-thaksalawa",
                "LINK":"https://www.e-thaksalawa.moe.gov.lk/moodle/mod/hvp/view.php?id=47140"
            }
        ],
        [
            {
                "EXAM_PAPER_PDF_TITLE":"Days",
                "LINK":"https://drive.google.com/file/d/1croZk-WkOqcgVZbGCkaTtprzUMCdAovZ/view?usp=sharing"
            },
            {
                "EXAM_PAPER_PDF_TITLE":"Fraction",
                "LINK":"https://drive.google.com/file/d/111SAYJcdgiNrz9RQ3GIFOp8E0sfBxJ4e/view?usp=sharing"
            },
            {
                "EXAM_PAPER_PDF_TITLE":"Meettal 01",
                "LINK":"https://drive.google.com/file/d/1xViQgGqVD76k3pTfWV34aWC3NzcX5ABY/view?usp=sharing"
            },
            {
                "EXAM_PAPER_PDF_TITLE":"Worksheet",
                "LINK":"https://drive.google.com/file/d/17l-6wc1qRvBOL2pXaemP87w1nY7SxR30/view?usp=sharing"
            },
            {
                "EXAM_PAPER_PDF_TITLE":"3rd Term Pro",
                "LINK":"https://drive.google.com/file/d/1I08jnHcPYLgl6Rf2uERJUny1aIlJ06uI/view?usp=sharing"
            }
        ],
        [
            {
                "EXAM_PAPER_PDF_TITLE":"Covid 19_Batticalo Paper",
                "LINK":"https://drive.google.com/file/d/1CNVBg-Aq9Ufc-DA5mUUpluKgyKMsPE9Y/view?usp=sharing"
            },
            {
                "EXAM_PAPER_PDF_TITLE":"Model Paper",
                "LINK":"https://drive.google.com/file/d/1C9RSC1wvsAoTUg2e0Ip07xkUVJoFBuR0/view?usp=sharing"
            },
            {
                "EXAM_PAPER_PDF_TITLE":"Activity 02",
                "LINK":"https://drive.google.com/file/d/1CUWtyRtvUVeGMTPnkVdsuQDqJXvIxQms/view?usp=sharing"
            },
            {
                "EXAM_PAPER_PDF_TITLE":"Model Paper 02",
                "LINK":"https://drive.google.com/file/d/1CViZFm3rrCIB0_sGlLVi1Kr_T3GX83YM/view?usp=sharing"
            },
            {
                "EXAM_PAPER_PDF_TITLE":"Worksheet",
                "LINK":"https://drive.google.com/file/d/1ACtNVHNlQC3vQqpAvwZ7E1IdqNVxFZsz/view?usp=sharing"
            }
        ],
        [
            {
                "EXAM_PAPER_PDF_TITLE":"Seminar Paper",
                "LINK":"https://drive.google.com/file/d/1aQ4-1SfJXtwEW9UfOjLEUvLhuZyZQG7W/view?usp=sharing"
            },
            {
                "EXAM_PAPER_PDF_TITLE":"Arivuththarahai Exam - 01",
                "LINK":"https://drive.google.com/file/d/1-VS3gQkx0VM2ZZIFv1YfARR27xZqxOVp/view?usp=sharing"
            },
            {
                "EXAM_PAPER_PDF_TITLE":"Arivuththarahai Exam - 02",
                "LINK":"https://drive.google.com/file/d/105PRj5ooAYncjG6Coiw8glKQVB7Vyb_q/view?usp=sharing"
            },
            {
                "EXAM_PAPER_PDF_TITLE":"அறிவுச் சுரங்கம் கணிதம் தொடர் 2 Ageenthan Sir",
                "LINK":"https://drive.google.com/file/d/18oMtZ8hiw2dI7vPSZhAIzk2dPgehVBVE/view?usp=sharing"
            },
            {
                "EXAM_PAPER_PDF_TITLE":"அறிவுச் சுரங்கம் கணிதம் தொடர் 8 Ageenthan Sir",
                "LINK":"https://drive.google.com/file/d/19x9Qwd9xrcT4z2t5ctcA8Ur2LTPjxZh_/view?usp=sharing"
            }
        ],
        [
            {
                "EXAM_PAPER_PDF_TITLE":"Worksheet",
                "LINK":"https://drive.google.com/file/d/1bm5vynYnQfUA0-r3B2J-iNUJNuqReKd_/view?usp=sharing"
            },
            {
                "EXAM_PAPER_PDF_TITLE":"1st Term Paper",
                "LINK":"https://drive.google.com/file/d/16vKD_S5C1h5VGG7JpsoDJq1IwcJURUVc/view?usp=sharing"
            },
            {
                "EXAM_PAPER_PDF_TITLE":"Worksheet 02",
                "LINK":"https://drive.google.com/file/d/1fpMO9DF-qUqY5nPBjqqEsfd-t9vWiWx8/view?usp=sharing"
            },
            {
                "EXAM_PAPER_PDF_TITLE":"Worksheet 03",
                "LINK":"https://drive.google.com/file/d/1M2EUixqSPuyzmVeWpTjs8GX-wTYiuZ21/view?usp=sharing"
            },
            {
                "EXAM_PAPER_PDF_TITLE":"Model Paper",
                "LINK":"https://drive.google.com/file/d/1EKcu0IhfTJ28iMTlkm8zFeVIuZWaAhS5/view?usp=sharing"
            }
        ],
        [
            {
                "EXAM_PAPER_PDF_TITLE":"Worksheet 01",
                "LINK":"https://drive.google.com/file/d/1GiOUK561fo8UD4V9P43J1AynVACb2pvy/view?usp=sharing"
            },
            {
                "EXAM_PAPER_PDF_TITLE":"Worksheet 02",
                "LINK":"https://drive.google.com/file/d/11HpytD1DbsGSOnVUvHntQSjMXEM3LqkO/view?usp=sharing"
            },
            {
                "EXAM_PAPER_PDF_TITLE":"Worksheet 03",
                "LINK":"https://drive.google.com/file/d/10jllvjvK7b8War9TOFil_rTuruH8OmOe/view?usp=sharing"
            },
            {
                "EXAM_PAPER_PDF_TITLE":"Worksheet 04",
                "LINK":"https://drive.google.com/file/d/11Ca_4DhxrWVwE1vSZuPOMqo3ZIsrqrOD/view?usp=sharing"
            }
        ],
        [
            {
                "EXAM_PAPER_PDF_TITLE":"1ம் தவணை 2018",
                "LINK":"https://drive.google.com/file/d/1lYSg8o96vvI78IFFx7dp0hajmb19-5Hs/view?usp=sharing"
            },
            {
                "EXAM_PAPER_PDF_TITLE":"3ம் தவணை 2018",
                "LINK":"https://drive.google.com/file/d/1M-fmMOHMZGD4pu4-y1HjTheCxLTi2EU4/view?usp=sharing"
            },
            {
                "EXAM_PAPER_PDF_TITLE":"Numbers",
                "LINK":"https://drive.google.com/file/d/1EpHIz3FqJOr4ItFWat6xzV0xLzAvrImO/view?usp=sharing"
            },
            {
                "EXAM_PAPER_PDF_TITLE":"Meettal",
                "LINK":"https://drive.google.com/file/d/1foyqLgEB4E7HkniIZCaB-TGQ5wFza9pK/view?usp=sharing"
            }
        ],
        [
            {
                "EXAM_PAPER_PDF_TITLE":"Model Paper",
                "LINK":"https://drive.google.com/file/d/1Gol8IubmHSI6CSqwaLlNHqhRCvKJA1uH/view?usp=sharing"
            },
            {
                "EXAM_PAPER_PDF_TITLE":"Sathaweedam",
                "LINK":"https://drive.google.com/file/d/1BTAHoE8SUfJtT4Hqu3J-HB9AIGrE3Hr2/view?usp=sharing"
            },
            {
                "EXAM_PAPER_PDF_TITLE":"Model Paper 02",
                "LINK":"https://drive.google.com/file/d/1B60lWopd8mR0SmQoOlJmUnP5vcd06M9T/view?usp=sharing"
            }
        ],
        [
            {
                "EXAM_PAPER_PDF_TITLE":"Model Paper",
                "LINK":"https://drive.google.com/file/d/1H6H8G5o64priFrnvCuTF4PydYIZP86Li/view?usp=sharing"
            },
            {
                "EXAM_PAPER_PDF_TITLE":"Workbook-1",
                "LINK":"https://drive.google.com/file/d/1AsYdt120VBhA3gF1dzP_1mSHJXeioaX1/view?usp=sharing"
            },
            {
                "EXAM_PAPER_PDF_TITLE":"Workbook 02",
                "LINK":"https://drive.google.com/file/d/1dwZ1FVm7PQkr4yYiaiZTgzBc2lKPnGZF/view?usp=sharing"
            },
            {
                "EXAM_PAPER_PDF_TITLE":"1st term 2018",
                "LINK":"https://drive.google.com/file/d/18wVT2mltZNRyc6t4IoRmp9PM0NbBfq2L/view?usp=sharing"
            },
            {
                "EXAM_PAPER_PDF_TITLE":"NWP_1st Term 2018",
                "LINK":"https://drive.google.com/file/d/18uWacbLvsktutlUZM7Zq57rF3Je9MdFQ/view?usp=sharing"
            }
        ],
        [
            {
                "EXAM_PAPER_PDF_TITLE":"book-Paper I",
                "LINK":"https://drive.google.com/file/d/1nC8T-38aLFoNsnSRyEpB-YFOvegVmfJp/view?usp=sharing"
            },
            {
                "EXAM_PAPER_PDF_TITLE":"பயிற்சி பரீட்சை-01",
                "LINK":"https://drive.google.com/file/d/1a8oX12Mbun_uipgDcfNfa-c4RNtCA43o/view?usp=sharing"
            },
            {
                "EXAM_PAPER_PDF_TITLE":"பயிற்சி பரீட்சை-02",
                "LINK":"https://drive.google.com/file/d/1dlJAubL-u87fXLs78N6_j79ohRrpQh3Z/view?usp=sharing"
            },
            {
                "EXAM_PAPER_PDF_TITLE":"பயிற்சி பரீட்சை-03",
                "LINK":"https://drive.google.com/file/d/1MiBbyzH_XwN1z62Y1RYg1FLBSNNkdC45/view?usp=sharing"
            },
            {
                "EXAM_PAPER_PDF_TITLE":"பயிற்சி பரீட்சை-05",
                "LINK":"https://drive.google.com/file/d/1Zhadzc0j4zPsKhsMjK3bJYIONYG8XrwZ/view?usp=sharing"
            }
        ],
        [
            {
                "EXAM_PAPER_PDF_TITLE":"Quadratic Equation and Function",
                "LINK":"https://drive.google.com/file/d/1YfAb4gsSO2YDIyDDS9lGgQ0TeV0bSR_-/view?usp=sharing"
            },
            {
                "EXAM_PAPER_PDF_TITLE":"Trigonometry",
                "LINK":"https://drive.google.com/file/d/191X9jqK68aLR6N3KNhZUYxLiTM29zwTc/view?usp=sharing"
            },
            {
                "EXAM_PAPER_PDF_TITLE":"Batticaloa 6th term paper",
                "LINK":"https://drive.google.com/file/d/14CntCIrTctDxJ-fGh0bfFPKmVXRRAg7X/view?usp=sharing"
            },
            {
                "EXAM_PAPER_PDF_TITLE":"Model Paper 2015",
                "LINK":"https://drive.google.com/file/d/1ViRHB-HQNXhlhvQCGaHXyKc5Sjt5AZJV/view?usp=sharing"
            },
            {
                "EXAM_PAPER_PDF_TITLE":"Model Paper 2018",
                "LINK":"https://drive.google.com/file/d/1pe8ttjwk4na2GLz25fnRJ8XJoA9VDwbU/view?usp=sharing"
            }
        ]
    ]
}